_libhfst_dev.cpython-38-x86_64-linux-gnu.so
libhfst_dev.py
hfst_dev/__init__.py
hfst_dev/exceptions/__init__.py
hfst_dev/sfst_rules/__init__.py
hfst_dev/xerox_rules/__init__.py
hfst_dev-3.15.0.10b0.dist-info/top_level.txt
hfst_dev-3.15.0.10b0.dist-info/WHEEL
hfst_dev-3.15.0.10b0.dist-info/METADATA
hfst_dev-3.15.0.10b0.dist-info/RECORD
