Metadata-Version: 2.1
Name: hfst-dev
Version: 3.15.0.10b0
Summary: Python interface for HFST
Home-page: http://hfst.github.io/
Author: HFST team
Author-email: hfst-bugs@helsinki.fi
License: GNU GPL3
Platform: UNKNOWN
